{"datastore": "local", "version": "1.0", "attempt": 0, "python_version": "3.10.12 (main, Nov 20 2023, 15:14:05) [GCC 11.4.0]", "objects": {"name": "1173f3a425f13b0a6e8bb6715d01692b99dca6d0", "dataset_file": "46ad5645dc859e6a812639f22fc0a88e9889f6b6", "_transition": "f3627f46179fdd95bf0e83101840fd1d71b60e40", "_task_ok": "69e77141c3eb7a8c9ce864251d70c02723f29332", "_success": "69e77141c3eb7a8c9ce864251d70c02723f29332", "_graph_info": "3cf867cd1dcaa182ef81b290e7cd843d6480cb9c", "_foreach_stack": "4ca058df2ea422cca260c585409d6ac9face7ebe"}, "info": {"name": {"size": 30, "type": "<class 'str'>", "encoding": "gzip+pickle-v2"}, "dataset_file": {"size": 30, "type": "<class 'str'>", "encoding": "gzip+pickle-v2"}, "_transition": {"size": 4, "type": "<class 'NoneType'>", "encoding": "gzip+pickle-v2"}, "_task_ok": {"size": 4, "type": "<class 'bool'>", "encoding": "gzip+pickle-v2"}, "_success": {"size": 4, "type": "<class 'bool'>", "encoding": "gzip+pickle-v2"}, "_graph_info": {"size": 506, "type": "<class 'dict'>", "encoding": "gzip+pickle-v2"}, "_foreach_stack": {"size": 6, "type": "<class 'list'>", "encoding": "gzip+pickle-v2"}}}